oknlabel/__init__.py
oknlabel/okn_detection_rule.json
oknlabel/oknlabel.py
oknlabel/oknlabel_config.json
oknlabel-1.1.2.dist-info/LICENSE
oknlabel-1.1.2.dist-info/METADATA
oknlabel-1.1.2.dist-info/WHEEL
oknlabel-1.1.2.dist-info/entry_points.txt
oknlabel-1.1.2.dist-info/top_level.txt
oknlabel-1.1.2.dist-info/RECORD
